archiver/__init__.py
archiver/mkarchive.py
archiver/selfextract0.c
archiver/setup.sh
installer/__init__.py
installer/smartsetup.py
mkarchive-0.6.0.data/data/archiver/selfextract0.c
mkarchive-0.6.0.data/data/archiver/setup.sh
mkarchive-0.6.0.dist-info/LICENSE
mkarchive-0.6.0.dist-info/METADATA
mkarchive-0.6.0.dist-info/WHEEL
mkarchive-0.6.0.dist-info/entry_points.txt
mkarchive-0.6.0.dist-info/top_level.txt
mkarchive-0.6.0.dist-info/RECORD
