Metadata-Version: 2.1
Name: mkarchive
Version: 0.6.0
Summary: Create Linux self-executables & installers based on 'dialog'
Home-page: https://github.com/destrangis/mkarchive
Author: Javier Llopis
Author-email: javier@llopis.me
License: UNKNOWN
Platform: UNKNOWN
Classifier: License :: OSI Approved :: MIT License
Classifier: Programming Language :: Python :: 3.7
Classifier: Programming Language :: Python :: 3.8
Classifier: Programming Language :: Python :: 3.9
Classifier: Development Status :: 4 - Beta
Classifier: Environment :: Console
Classifier: Intended Audience :: Developers
Classifier: Intended Audience :: End Users/Desktop
Classifier: Intended Audience :: System Administrators
Classifier: Operating System :: POSIX
Classifier: Topic :: System :: Archiving :: Packaging
Classifier: Topic :: System :: Software Distribution
Classifier: Topic :: System :: Installation/Setup
Classifier: Topic :: Utilities
License-File: LICENSE
Requires-Dist: PyYAML
Requires-Dist: importlib-resources ; python_version < "3.9.0"
